kernel_killer/__init__.py
kernel_killer/_version.py
kernel_killer/handlers.py
kernel_killer-0.1.2.data/data/etc/jupyter/jupyter_notebook_config.d/kernel_killer.json
kernel_killer-0.1.2.data/data/etc/jupyter/jupyter_server_config.d/kernel_killer.json
kernel_killer-0.1.2.data/data/share/jupyter/labextensions/kernel_killer/package.json
kernel_killer-0.1.2.data/data/share/jupyter/labextensions/kernel_killer/static/568.b4a9ee55c19f93910367.js
kernel_killer-0.1.2.data/data/share/jupyter/labextensions/kernel_killer/static/747.213725e83c76da646665.js
kernel_killer-0.1.2.data/data/share/jupyter/labextensions/kernel_killer/static/remoteEntry.836d352aff1a1f7dad46.js
kernel_killer-0.1.2.data/data/share/jupyter/labextensions/kernel_killer/static/style.js
kernel_killer-0.1.2.data/data/share/jupyter/labextensions/kernel_killer/static/third-party-licenses.json
kernel_killer-0.1.2.data/data/share/jupyter/labextensions/kernel_killer/install.json
kernel_killer-0.1.2.dist-info/METADATA
kernel_killer-0.1.2.dist-info/WHEEL
kernel_killer-0.1.2.dist-info/licenses/LICENSE
kernel_killer-0.1.2.dist-info/RECORD
