Metadata-Version: 2.1
Name: kernel_killer
Version: 0.1.2
Summary: Extension to kill kernel on tab closing
Project-URL: Homepage, https://github.com/github_username/kernel_killer
Project-URL: Bug Tracker, https://github.com/github_username/kernel_killer/issues
Project-URL: Repository, https://github.com/github_username/kernel_killer.git
Author-email: Vinícius Costa <viniciuslc476@gmail.com>
License: BSD 3-Clause License
License-File: LICENSE
Classifier: Framework :: Jupyter
Classifier: Framework :: Jupyter :: JupyterLab
Classifier: Framework :: Jupyter :: JupyterLab :: 4
Classifier: Framework :: Jupyter :: JupyterLab :: Extensions
Classifier: Framework :: Jupyter :: JupyterLab :: Extensions :: Prebuilt
Classifier: License :: OSI Approved :: BSD License
Classifier: Programming Language :: Python
Classifier: Programming Language :: Python :: 3
Classifier: Programming Language :: Python :: 3.8
Classifier: Programming Language :: Python :: 3.9
Classifier: Programming Language :: Python :: 3.10
Classifier: Programming Language :: Python :: 3.11
Requires-Python: >=3.8
Requires-Dist: jupyter-server<3,>=2.0.1
